samdasoo_content-0.3.0.dist-info/METADATA
samdasoo_content-0.3.0.dist-info/WHEEL
samdasoo_content/__init__.py
samdasoo_content/content.py
samdasoo_content-0.3.0.dist-info/RECORD
