Metadata-Version: 2.1
Name: samdasoo-content
Version: 0.3.0
Summary: Let me tell you about Samdasoo, Korea's representative bottled water.
Author-Email: dmario24 <data.mario24@gmail.com>
License: MIT
Project-URL: Homepage, https://github.com/dmario24/samdasoo-content
Project-URL: Bug tracker, https://github.com/dmario24/samdasoo-content/issues
Requires-Python: >=3.9
